nba_tracking_plotly/__init__.py
nba_tracking_plotly/fullcourt.png
platyhelminthes/__init__.py
nba_tracking_plotly-0.0.1.12.dist-info/LICENSE
nba_tracking_plotly-0.0.1.12.dist-info/METADATA
nba_tracking_plotly-0.0.1.12.dist-info/WHEEL
nba_tracking_plotly-0.0.1.12.dist-info/top_level.txt
nba_tracking_plotly-0.0.1.12.dist-info/RECORD
