Metadata-Version: 2.1
Name: nba-tracking-plotly
Version: 0.0.1.12
Summary: Plot nba tracking data using plotly
Home-page: https://github.com/avyayv/nba_tracking_plotly
Author: Avyay Varadarajan
Author-email: avyayv@gmail.com
License: UNKNOWN
Platform: UNKNOWN
Classifier: Programming Language :: Python :: 3
Classifier: License :: OSI Approved :: MIT License
Classifier: Operating System :: OS Independent
Requires-Python: >=3.6
